Metadata-Version: 2.1
Name: pylsd-nova-mac-arm
Version: 1.2.0
Summary: Fork of pylsd-nova that supports MAC arm (m1)
Home-page: https://github.com/AndranikSargsyan/pylsd-nova
Author: Andranik Sargsyan
Author-email: and.sargsyan@yahoo.com
License: BSD
Keywords: LSD
Platform: UNKNOWN
License-File: LICENSE
